aliyunsdkvs/__init__.py
aliyunsdkvs/endpoint.py
aliyunsdkvs/request/__init__.py
aliyunsdkvs/request/v20181212/AddDeviceRequest.py
aliyunsdkvs/request/v20181212/AddRenderingDeviceInternetPortsRequest.py
aliyunsdkvs/request/v20181212/AddVsPullStreamInfoConfigRequest.py
aliyunsdkvs/request/v20181212/BatchBindDirectoriesRequest.py
aliyunsdkvs/request/v20181212/BatchBindParentPlatformDevicesRequest.py
aliyunsdkvs/request/v20181212/BatchBindPurchasedDevicesRequest.py
aliyunsdkvs/request/v20181212/BatchBindTemplateRequest.py
aliyunsdkvs/request/v20181212/BatchBindTemplatesRequest.py
aliyunsdkvs/request/v20181212/BatchDeleteDevicesRequest.py
aliyunsdkvs/request/v20181212/BatchDeleteVsDomainConfigsRequest.py
aliyunsdkvs/request/v20181212/BatchForbidVsStreamRequest.py
aliyunsdkvs/request/v20181212/BatchResumeVsStreamRequest.py
aliyunsdkvs/request/v20181212/BatchSetVsDomainConfigsRequest.py
aliyunsdkvs/request/v20181212/BatchStartDevicesRequest.py
aliyunsdkvs/request/v20181212/BatchStartStreamsRequest.py
aliyunsdkvs/request/v20181212/BatchStopDevicesRequest.py
aliyunsdkvs/request/v20181212/BatchStopStreamsRequest.py
aliyunsdkvs/request/v20181212/BatchUnbindDirectoriesRequest.py
aliyunsdkvs/request/v20181212/BatchUnbindParentPlatformDevicesRequest.py
aliyunsdkvs/request/v20181212/BatchUnbindPurchasedDevicesRequest.py
aliyunsdkvs/request/v20181212/BatchUnbindTemplateRequest.py
aliyunsdkvs/request/v20181212/BatchUnbindTemplatesRequest.py
aliyunsdkvs/request/v20181212/BindDirectoryRequest.py
aliyunsdkvs/request/v20181212/BindParentPlatformDeviceRequest.py
aliyunsdkvs/request/v20181212/BindPurchasedDeviceRequest.py
aliyunsdkvs/request/v20181212/BindTemplateRequest.py
aliyunsdkvs/request/v20181212/ContinuousAdjustRequest.py
aliyunsdkvs/request/v20181212/ContinuousMoveRequest.py
aliyunsdkvs/request/v20181212/CreateClusterRequest.py
aliyunsdkvs/request/v20181212/CreateDeviceAlarmRequest.py
aliyunsdkvs/request/v20181212/CreateDeviceRequest.py
aliyun_python_sdk_vs-1.10.4.dist-info/LICENSE
aliyun_python_sdk_vs-1.10.4.dist-info/METADATA
aliyun_python_sdk_vs-1.10.4.dist-info/WHEEL
aliyun_python_sdk_vs-1.10.4.dist-info/top_level.txt
aliyun_python_sdk_vs-1.10.4.dist-info/RECORD
